lnPi/__init__.py
lnPi/collectionlnpiutils.py
lnPi/maskedlnpi_legacy.py
lnPi/stability.py
lnpy/__init__.py
lnpy/_compat.py
lnpy/_typing.py
lnpy/_typing_compat.py
lnpy/bracket.py
lnpy/combine.py
lnpy/docstrings.py
lnpy/ensembles.py
lnpy/examples.py
lnpy/extensions.py
lnpy/lnpicollectionutils.py
lnpy/lnpidata.py
lnpy/lnpienergy.py
lnpy/lnpiseries.py
lnpy/molfrac.py
lnpy/options.py
lnpy/py.typed
lnpy/segment.py
lnpy/stability.py
lnpy/utils.py
lnpy/data/hsmix_example.json.gz
lnpy/data/lj_sub_example.json
lnpy/data/lj_sup_example.json
lnpy/data/ljmix_sup_example.json.gz
lnpy/data/watermof_example.json
tmmc_lnpy-0.8.0.dist-info/METADATA
tmmc_lnpy-0.8.0.dist-info/WHEEL
tmmc_lnpy-0.8.0.dist-info/licenses/LICENSE
tmmc_lnpy-0.8.0.dist-info/RECORD
