Metadata-Version: 2.1
Name: tmmc-lnpy
Version: 0.8.0
Summary: Analysis of lnPi results from TMMC simulation
Project-URL: Documentation, https://pages.nist.gov/tmmc-lnpy/
Project-URL: Homepage, https://github.com/usnistgov/tmmc-lnpy
Author-email: "William P. Krekelberg" <wpk@nist.gov>
License: NIST-PD
License-File: LICENSE
Keywords: tmmc-lnpy
Classifier: Development Status :: 2 - Pre-Alpha
Classifier: Intended Audience :: Science/Research
Classifier: License :: Public Domain
Classifier: Operating System :: OS Independent
Classifier: Programming Language :: Python
Classifier: Programming Language :: Python :: 3 :: Only
Classifier: Programming Language :: Python :: 3.8
Classifier: Programming Language :: Python :: 3.9
Classifier: Programming Language :: Python :: 3.10
Classifier: Programming Language :: Python :: 3.11
Classifier: Programming Language :: Python :: 3.12
Classifier: Topic :: Scientific/Engineering
Requires-Python: <=3.12,>=3.8
Requires-Dist: bottleneck
Requires-Dist: importlib-resources; python_version < '3.10'
Requires-Dist: joblib
Requires-Dist: lazy-loader
Requires-Dist: module-utilities>=0.9.0
Requires-Dist: numpy
Requires-Dist: scikit-image>=0.21
Requires-Dist: scipy
Requires-Dist: tqdm
Requires-Dist: typing-extensions; python_version < '3.11'
Requires-Dist: xarray
Provides-Extra: dev
Requires-Dist: tmmc-lnpy[dev-extras,mypy,nbval,pipxrun,test,typing,viz]; extra == 'dev'
Provides-Extra: dev-complete
Requires-Dist: tmmc-lnpy[dev,tools]; extra == 'dev-complete'
Provides-Extra: dev-extras
Requires-Dist: ipykernel; extra == 'dev-extras'
Requires-Dist: ipython; extra == 'dev-extras'
Requires-Dist: nbclient>=0.10.0; extra == 'dev-extras'
Requires-Dist: nox>=2024.3.2; extra == 'dev-extras'
Requires-Dist: pytest-accept; extra == 'dev-extras'
Provides-Extra: docs
Requires-Dist: autodocsumm; extra == 'docs'
Requires-Dist: myst-nb; extra == 'docs'
Requires-Dist: pyenchant; extra == 'docs'
Requires-Dist: sphinx-autobuild; extra == 'docs'
Requires-Dist: sphinx-book-theme; extra == 'docs'
Requires-Dist: sphinx-copybutton; extra == 'docs'
Requires-Dist: sphinx>=5.3.0; extra == 'docs'
Requires-Dist: sphinxcontrib-spelling; extra == 'docs'
Requires-Dist: tmmc-lnpy[viz]; extra == 'docs'
Provides-Extra: mypy
Requires-Dist: mypy>=1.9.0; extra == 'mypy'
Provides-Extra: nbval
Requires-Dist: nbval; extra == 'nbval'
Provides-Extra: pipxrun
Requires-Dist: packaging; extra == 'pipxrun'
Provides-Extra: pipxrun-tools
Requires-Dist: conda-lock>=2.5.5; extra == 'pipxrun-tools'
Requires-Dist: grayskull>=2.5.3; extra == 'pipxrun-tools'
Requires-Dist: nbqa>=1.8.4; extra == 'pipxrun-tools'
Requires-Dist: pyright!=1.1.358,>=1.1.357; extra == 'pipxrun-tools'
Requires-Dist: tmmc-lnpy[mypy]; extra == 'pipxrun-tools'
Requires-Dist: twine>=5.0.0; extra == 'pipxrun-tools'
Provides-Extra: test
Requires-Dist: pytest; extra == 'test'
Requires-Dist: pytest-cov; extra == 'test'
Requires-Dist: pytest-sugar; extra == 'test'
Requires-Dist: pytest-xdist; extra == 'test'
Provides-Extra: tools
Requires-Dist: pipx; extra == 'tools'
Requires-Dist: pre-commit; extra == 'tools'
Requires-Dist: scriv; extra == 'tools'
Provides-Extra: typing
Requires-Dist: pandas-stubs; extra == 'typing'
Requires-Dist: pytest; extra == 'typing'
Requires-Dist: tmmc-lnpy[pipxrun]; extra == 'typing'
Requires-Dist: types-tqdm; extra == 'typing'
Provides-Extra: viz
Requires-Dist: ipywidgets; extra == 'viz'
Requires-Dist: matplotlib; extra == 'viz'
